labelboxbigquery/__init__.py
labelboxbigquery/client.py
labelboxbigquery/connector.py
labelboxbigquery-0.1.7.dist-info/LICENSE
labelboxbigquery-0.1.7.dist-info/METADATA
labelboxbigquery-0.1.7.dist-info/WHEEL
labelboxbigquery-0.1.7.dist-info/top_level.txt
labelboxbigquery-0.1.7.dist-info/RECORD
