Metadata-Version: 2.1
Name: labelboxbigquery
Version: 0.1.7
Summary: Labelbox Connector for BigQuery
Home-page: https://labelbox.com
Author: Labelbox
Author-email: raphael@labelbox.com
Keywords: labelbox,bigquery,labelboxbigquery,labelbase
License-File: LICENSE
Requires-Dist: labelbox
Requires-Dist: google-cloud-bigquery
Requires-Dist: labelbase
